MANIFEST.in
README.rst
setup.py
kaleo/__init__.py
kaleo/admin.py
kaleo/compat.py
kaleo/conf.py
kaleo/forms.py
kaleo/models.py
kaleo/receivers.py
kaleo/signals.py
kaleo/stats.py
kaleo/urls.py
kaleo/views.py
kaleo.egg-info/PKG-INFO
kaleo.egg-info/SOURCES.txt
kaleo.egg-info/dependency_links.txt
kaleo.egg-info/not-zip-safe
kaleo.egg-info/requires.txt
kaleo.egg-info/top_level.txt
kaleo/management/__init__.py
kaleo/management/commands/__init__.py
kaleo/management/commands/add_invites.py
kaleo/management/commands/infinite_invites.py
kaleo/management/commands/topoff_invites.py
kaleo/templates/kaleo/_invite_form.html
kaleo/templates/kaleo/_invited.html
kaleo/templates/kaleo/_invites_remaining.html
kaleo/templatetags/__init__.py
kaleo/templatetags/kaleo_tags.py
kaleo/tests/__init__.py
kaleo/tests/models.py
kaleo/tests/tests.py
kaleo/tests/urls.py